fluyd/__init__.py
fluyd-0.1.0.dist-info/LICENSE
fluyd-0.1.0.dist-info/WHEEL
fluyd-0.1.0.dist-info/METADATA
fluyd-0.1.0.dist-info/RECORD
